tvrcoint/__init__.py
tvrcoint/bootstrap.py
tvrcoint/chebyshev.py
tvrcoint/critical_values.py
tvrcoint/lr_test.py
tvrcoint/matrices.py
tvrcoint/output.py
tvrcoint/simulation.py
tvrcoint/tvvecm.py
tvrcoint/utils.py
tvrcoint-1.0.0.dist-info/licenses/LICENSE
tvrcoint-1.0.0.dist-info/METADATA
tvrcoint-1.0.0.dist-info/WHEEL
tvrcoint-1.0.0.dist-info/top_level.txt
tvrcoint-1.0.0.dist-info/RECORD
