Metadata-Version: 2.4
Name: tvrcoint
Version: 1.0.0
Summary: Time-Varying Cointegration Tests - Bootstrap LR tests for time-varying cointegration based on Bierens & Martins (2010) and Martins (2015)
Author-email: Dr Merwan Roudane <merwanroudane920@gmail.com>
Maintainer-email: Dr Merwan Roudane <merwanroudane920@gmail.com>
License: MIT
Project-URL: Homepage, https://github.com/merwanroudane/tvrcoint
Project-URL: Documentation, https://github.com/merwanroudane/tvrcoint#readme
Project-URL: Repository, https://github.com/merwanroudane/tvrcoint.git
Project-URL: Issues, https://github.com/merwanroudane/tvrcoint/issues
Keywords: cointegration,time-varying,econometrics,bootstrap,VECM,likelihood ratio test,Chebyshev polynomials,purchasing power parity
Classifier: Development Status :: 4 - Beta
Classifier: Intended Audience :: Science/Research
Classifier: Intended Audience :: Education
Classifier: License :: OSI Approved :: MIT License
Classifier: Operating System :: OS Independent
Classifier: Programming Language :: Python :: 3
Classifier: Programming Language :: Python :: 3.8
Classifier: Programming Language :: Python :: 3.9
Classifier: Programming Language :: Python :: 3.10
Classifier: Programming Language :: Python :: 3.11
Classifier: Programming Language :: Python :: 3.12
Classifier: Topic :: Scientific/Engineering :: Mathematics
Classifier: Topic :: Scientific/Engineering :: Information Analysis
Requires-Python: >=3.8
License-File: LICENSE
Requires-Dist: numpy>=1.20.0
Requires-Dist: scipy>=1.7.0
Requires-Dist: pandas>=1.3.0
Provides-Extra: dev
Requires-Dist: pytest>=7.0.0; extra == "dev"
Requires-Dist: pytest-cov>=4.0.0; extra == "dev"
Requires-Dist: black>=23.0.0; extra == "dev"
Requires-Dist: isort>=5.12.0; extra == "dev"
Requires-Dist: mypy>=1.0.0; extra == "dev"
Provides-Extra: docs
Requires-Dist: sphinx>=5.0.0; extra == "docs"
Requires-Dist: sphinx-rtd-theme>=1.0.0; extra == "docs"
Dynamic: license-file
